jgtfx2console/LiveChartDataExport.py
jgtfx2console/__init__.py
jgtfx2console/config_generator.py
jgtfx2console/fxcli2console.py
jgtfx2console/common_samples/BatchOrderMonitor.py
jgtfx2console/common_samples/OrderMonitor.py
jgtfx2console/common_samples/OrderMonitorNetting.py
jgtfx2console/common_samples/TableListenerContainer.py
jgtfx2console/common_samples/__init__.py
jgtfx2console/common_samples/common.py
jgtfx2console/forexconnect/EachRowListener.py
jgtfx2console/forexconnect/ForexConnect.py
jgtfx2console/forexconnect/LiveHistory.py
jgtfx2console/forexconnect/ResponseListener.py
jgtfx2console/forexconnect/SessionStatusListener.py
jgtfx2console/forexconnect/TableListener.py
jgtfx2console/forexconnect/TableManagerListener.py
jgtfx2console/forexconnect/__init__.py
jgtfx2console/forexconnect/_fix_import.sh
jgtfx2console/forexconnect/common.py
jgtfx2console/forexconnect/errors.py
jgtfx2console/forexconnect/x-pyd.py
jgtfx2console/forexconnect/lib/linux/__init__.py
jgtfx2console/forexconnect/lib/linux/fxcorepy.so
jgtfx2console/forexconnect/lib/linux/libForexConnect.so
jgtfx2console/forexconnect/lib/linux/libboost_python3.so.1.64.0
jgtfx2console/forexconnect/lib/linux/libboost_system.so.1.64.0
jgtfx2console/forexconnect/lib/linux/libfxmsg.so
jgtfx2console/forexconnect/lib/linux/libfxtp.so
jgtfx2console/forexconnect/lib/linux/libgsexpat.so
jgtfx2console/forexconnect/lib/linux/libgstool3.so
jgtfx2console/forexconnect/lib/linux/libhttplib.so
jgtfx2console/forexconnect/lib/linux/liblog4cplus.so
jgtfx2console/forexconnect/lib/linux/liblogger.so
jgtfx2console/forexconnect/lib/linux/libpdas.so
jgtfx2console/forexconnect/lib/linux/libpricehistorymgr.so.2.8.0
jgtfx2console/forexconnect/lib/linux/libpython3.7m.so
jgtfx2console/forexconnect/lib/linux/libquotesmgr2.so.2.8
jgtfx2console/forexconnect/lib/linux/libsqlite3.8.so
jgtfx2console/forexconnect/lib/linux/requirements.txt
jgtfx2console/forexconnect/lib/windows/ForexConnect.dll
jgtfx2console/forexconnect/lib/windows/__init__.py
jgtfx2console-0.5.15.dist-info/LICENSE
jgtfx2console-0.5.15.dist-info/METADATA
jgtfx2console-0.5.15.dist-info/WHEEL
jgtfx2console-0.5.15.dist-info/entry_points.txt
jgtfx2console-0.5.15.dist-info/top_level.txt
jgtfx2console-0.5.15.dist-info/RECORD
