Metadata-Version: 2.2
Name: jgtfx2console
Version: 0.5.15
Summary: PDS Services
Home-page: https://github.com/jgwill/jgtfx2console
Author: GUillaume Isabelle
Author-email: Guillaume Isabelle <jgi@jgwill.com>
Project-URL: Homepage, https://github.com/jgwill/jgtfx2console
Project-URL: Bug Tracker, https://github.com/jgwill/jgtfx2console/issues
Keywords: data
Classifier: Programming Language :: Python :: 3
Classifier: License :: OSI Approved :: MIT License
Classifier: Operating System :: OS Independent
Requires-Python: >=3.7
License-File: LICENSE
Requires-Dist: pandas>=0.25.1
Requires-Dist: python-dotenv>=0.19.2
Requires-Dist: jgtutils>=0.2.218
Requires-Dist: tlid
Provides-Extra: dev-lint
Requires-Dist: flake8<3.7.0,>=3.6.0; extra == "dev-lint"
Requires-Dist: isort<4.4.0,>=4.3.4; extra == "dev-lint"
Provides-Extra: dev-test
Requires-Dist: coverage; extra == "dev-test"
Requires-Dist: pytest>=3.10; extra == "dev-test"
Provides-Extra: dev-docs
Requires-Dist: readme_renderer; extra == "dev-docs"
Requires-Dist: sphinx; extra == "dev-docs"
Requires-Dist: sphinx_rtd_theme>=0.4.0; extra == "dev-docs"
Requires-Dist: html2text>=2020.1.16; extra == "dev-docs"
Requires-Dist: html2markdown>=0.1.7; extra == "dev-docs"
Dynamic: author
Dynamic: home-page
